auto_live_reload/__init__.py
auto_live_reload/live_reload.py
auto_live_reload-1.0.2.dist-info/licenses/LICENSE
auto_live_reload-1.0.2.dist-info/METADATA
auto_live_reload-1.0.2.dist-info/WHEEL
auto_live_reload-1.0.2.dist-info/top_level.txt
auto_live_reload-1.0.2.dist-info/RECORD
