Metadata-Version: 2.4
Name: auto-live-reload
Version: 1.0.2
Summary: A Python library for live reloading scripts on file changes.
Home-page: https://github.com/CrypterENC/auto-live-reload.git
Author: CrypterENC
Author-email: CrypterENC <a95899003@gmail.com>
License-Expression: MIT
Project-URL: Documentation, https://github.com/CrypterENC/auto-live-reload/blob/main/DOCUMENTATION.md
Project-URL: Repository, https://github.com/CrypterENC/auto-live-reload.git
Requires-Python: >=3.8
License-File: LICENSE
Dynamic: author
Dynamic: home-page
Dynamic: license-file
Dynamic: requires-python
